astillero/__init__.py
astillero-0.0.0a0.dist-info/METADATA
astillero-0.0.0a0.dist-info/WHEEL
astillero-0.0.0a0.dist-info/top_level.txt
astillero-0.0.0a0.dist-info/RECORD
