Metadata-Version: 2.4
Name: astillero
Version: 0.0.0a0
Summary: ⚠️  Placeholder release for the upcoming Astillero.
Author: Germán
License: Apache-2.0
Classifier: Development Status :: 1 - Planning
Classifier: License :: OSI Approved :: Apache Software License
Classifier: Programming Language :: Python :: 3
Requires-Python: >=3.9
